Metadata-Version: 2.4
Name: PGAP2
Version: 1.0.8
Summary: PGAP2: a comprehensive pan-genome analysis pipeline for prokaryotic genomes
Author-email: bucongfan <bucf@big.ac.cn>
Maintainer-email: bucongfan <bucf@big.ac.cn>
License: MIT License
Project-URL: homepage, https://github.com/bucongfan/PGAP2
Project-URL: documentation, https://github.com/bucongfan/PGAP2/wiki
Project-URL: repository, https://github.com/bucongfan/PGAP2
Keywords: pan-genome,prokaryotic,genomes,pipeline,cluster
Requires-Python: >=3.10
License-File: LICENSE
Requires-Dist: biopython==1.82
Requires-Dist: networkx==3.3
Requires-Dist: pyfastani==0.5.1
Requires-Dist: edlib==1.3.9
Requires-Dist: loguru==0.6.0
Requires-Dist: numpy==1.23.3
Requires-Dist: pandas==1.5.0
Requires-Dist: pyecharts==2.0.1
Requires-Dist: scikit_learn==1.1.2
Requires-Dist: scipy==1.9.1
Requires-Dist: tqdm==4.64.1
Requires-Dist: bcbio-gff==0.7.1
Requires-Dist: ete3==3.1.3
Requires-Dist: svgwrite==1.4.3
Requires-Dist: miniFasta==3.0.2
Requires-Dist: tajimas_d==2.0.2
Dynamic: license-file
